[
    {
        "Postcode": "95900",
        "Location": "Kampung Melayu",
        "Post_Office": "Lubok Antu",
        "State": "Sarawak"
    },
    {
        "Postcode": "95900",
        "Location": "Batang Ai",
        "Post_Office": "Lubok Antu",
        "State": "Sarawak"
    },
    {
        "Postcode": "95900",
        "Location": "Kampung Kutai",
        "Post_Office": "Lubok Antu",
        "State": "Sarawak"
    },
    {
        "Postcode": "95900",
        "Location": "Lubuk Antu",
        "Post_Office": "Lubok Antu",
        "State": "Sarawak"
    },
    {
        "Postcode": "95900",
        "Location": "Merindun",
        "Post_Office": "Lubok Antu",
        "State": "Sarawak"
    },
    {
        "Postcode": "95900",
        "Location": "Nanga Mepi",
        "Post_Office": "Lubok Antu",
        "State": "Sarawak"
    }
]
